hubspot_api/__init__.py
hubspot_api/api_client.py
hubspot_api/conversations.py
hubspot_api/login.py
hubspot_api/classes/__init__.py
hubspot_api/classes/ably.py
hubspot_api/classes/agents.py
hubspot_api/classes/assignee.py
hubspot_api/classes/message.py
hubspot_api/classes/threads.py
hubspot_api-0.7.0.dist-info/METADATA
hubspot_api-0.7.0.dist-info/WHEEL
hubspot_api-0.7.0.dist-info/top_level.txt
hubspot_api-0.7.0.dist-info/RECORD
