Metadata-Version: 2.1
Name: hubspot-api
Version: 0.7.0
Summary: Python library to interact with HubSpot's Private API
Home-page: https://github.com/Erol444/hubspot-api
Author: Erol444
Author-email: erol123444@gmail.com
Classifier: Development Status :: 3 - Alpha
Classifier: Intended Audience :: Developers
Classifier: License :: OSI Approved :: MIT License
Classifier: Programming Language :: Python :: 3
Classifier: Programming Language :: Python :: 3.6
Classifier: Programming Language :: Python :: 3.7
Classifier: Programming Language :: Python :: 3.8
Classifier: Programming Language :: Python :: 3.9
Classifier: Programming Language :: Python :: 3.10
Requires-Python: >=3.6
Requires-Dist: requests
